pyember-0.0.17.dist-info/METADATA
pyember-0.0.17.dist-info/RECORD
pyember-0.0.17.dist-info/top_level.txt
pyember-0.0.17.dist-info/WHEEL
ember/aten.cpython-311-x86_64-linux-gnu.so
ember/__init__.py
ember/__init__.pyi
ember/optimizers/__init__.py
ember/optimizers/optimizer.py
ember/models/__init__.py
ember/models/unsupervised/k_means.py
ember/models/unsupervised/__init__.py
ember/models/supervised/ensemble.py
ember/models/supervised/logistic_regression.py
ember/models/supervised/linear_regression.py
ember/models/supervised/__init__.py
ember/models/supervised/tree.py
ember/models/supervised/mlp.py
ember/models/supervised/nearest_neighbor.py
ember/datasets/cross_validation.py
ember/datasets/standardize.py
ember/datasets/__init__.py
ember/datasets/dataloader.py
ember/datasets/dataset.py
ember/objectives/loss.py
ember/objectives/__init__.py
ember/objectives/regularizer.py
ember/samplers/sampler.py
ember/samplers/__init__.py
