Metadata-Version: 2.1
Name: pyember
Version: 0.0.17
Summary: A statistics and machine learning package.
Author-email: Muchang Bahng <bahngmc@gmail.com>
Project-URL: Homepage, https://github.com/mbahng/pyember
Keywords: machine learning,autograd,deep learning,statistics
Requires-Python: >=3.9
Requires-Dist: pybind11>=2.10.0
